CHANGES.rst
MANIFEST.in
README.rst
setup.py
starzel/__init__.py
starzel.whoiscalling.egg-info/PKG-INFO
starzel.whoiscalling.egg-info/SOURCES.txt
starzel.whoiscalling.egg-info/dependency_links.txt
starzel.whoiscalling.egg-info/entry_points.txt
starzel.whoiscalling.egg-info/requires.txt
starzel.whoiscalling.egg-info/top_level.txt
starzel/whoiscalling/__init__.py
starzel/whoiscalling/bot.py