Metadata-Version: 1.1
Name: starzel.whoiscalling
Version: 0.0.2
Summary: Retrieve calling info from Fritzbox, expose to jabber Multi User Chatroom
Home-page: https://github.com/do3cc/starzel.whoiscalling
Author: Patrick Gerken
Author-email: gerken@patrick-gerken.de
License: BSD
Keywords: FRITZ!Box fritzbox jabber
Platform: UNKNOWN
Classifier: Development Status :: 3 - Alpha
Classifier: License :: OSI Approved :: BSD License
Classifier: Topic :: Communications :: Chat
Classifier: Topic :: Communications :: Telephony
